MANIFEST.in
README.rst
requirements.txt
setup.py
upload.sh
wxReply/__init__.py
wxReply/test.py
wxReply/wechat.py
wxReply/wxReply.py
wxReply.egg-info/PKG-INFO
wxReply.egg-info/SOURCES.txt
wxReply.egg-info/dependency_links.txt
wxReply.egg-info/requires.txt
wxReply.egg-info/top_level.txt