Metadata-Version: 1.1
Name: wxReply
Version: 1.2.6
Summary: wxReply
Home-page: https://github.com/tianshl/wxReply
Author: tianshl
Author-email: xiyuan91@126.com
License: MIT
Keywords: wechat robot weixin wxReply
Platform: UNKNOWN
Classifier: Development Status :: 3 - Alpha
Classifier: Intended Audience :: Developers
Classifier: Topic :: Software Development :: Libraries :: Python Modules
Classifier: License :: OSI Approved :: MIT License
Classifier: Programming Language :: Python :: 2
Classifier: Programming Language :: Python :: 2.7
Classifier: Programming Language :: Python :: 3
Classifier: Programming Language :: Python :: 3.3
Classifier: Programming Language :: Python :: 3.4
Classifier: Programming Language :: Python :: 3.5
